{"municipio":{"slug":"balneario_da_barra_do_sul","nome":"Balneário Da Barra Do Sul","n_pontos":3,"n_proprias":2,"n_improprias":1,"n_sem_dados":0,"pct_proprias":66.7,"lat":-26.4557,"lon":-48.6113},"pontos":[{"id":"ima_150","codigo_ima":"150","praia":"Canal Do Linguado","municipio":"Balneário Da Barra Do Sul","municipio_slug":"balneario_da_barra_do_sul","ponto_num":2,"descricao":"Na Prainha da foz do Canal Do Linguado","lat":-26.455229155902,"lon":-48.597740383673,"ultimo_status":"propria","ultima_coleta":"2026-05-26","semanas_proprias_consecutivas":5,"pct_proprias_historico":100.0,"total_coletas":5,"tem_historico_pdf":false},{"id":"ima_340","codigo_ima":"340","praia":"Canal Do Linguado","municipio":"Balneário Da Barra Do Sul","municipio_slug":"balneario_da_barra_do_sul","ponto_num":3,"descricao":"Em frente à Rua Otto Fiedler","lat":-26.44272,"lon":-48.628056,"ultimo_status":"impropria","ultima_coleta":"2026-05-26","semanas_proprias_consecutivas":0,"pct_proprias_historico":0.0,"total_coletas":5,"tem_historico_pdf":false},{"id":"ima_149","codigo_ima":"149","praia":"Praia Da Barra Do Sul","municipio":"Balneário Da Barra Do Sul","municipio_slug":"balneario_da_barra_do_sul","ponto_num":1,"descricao":"Na Praia do Bispo, em frente à Capela Dos Navegantes","lat":-26.469155226388,"lon":-48.608029709939,"ultimo_status":"propria","ultima_coleta":"2026-05-26","semanas_proprias_consecutivas":4,"pct_proprias_historico":80.0,"total_coletas":5,"tem_historico_pdf":false}]}