{"ponto":{"id":"ima_271","codigo_ima":"271","praia":"Praia Da Base Aérea","municipio":"Florianópolis","municipio_slug":"florianopolis","ponto_num":49,"descricao":"Ao lado do trapiche","lat":-27.67747112330876,"lon":-48.56779522552024,"ultimo_status":"propria","ultima_coleta":"2026-05-25","semanas_proprias_consecutivas":70,"pct_proprias_historico":97.8,"total_coletas":91,"tem_historico_pdf":true},"historico":[{"data":"2023-01-25","status":"propria","relatorio":10,"temporada":"2022-2023","fonte":"pdf"},{"data":"2023-02-01","status":"propria","relatorio":11,"temporada":"2022-2023","fonte":"pdf"},{"data":"2023-02-08","status":"propria","relatorio":12,"temporada":"2022-2023","fonte":"pdf"},{"data":"2023-02-15","status":"propria","relatorio":13,"temporada":"2022-2023","fonte":"pdf"},{"data":"2023-02-22","status":"impropria","relatorio":14,"temporada":"2022-2023","fonte":"pdf"},{"data":"2023-03-01","status":"propria","relatorio":15,"temporada":"2022-2023","fonte":"pdf"},{"data":"2023-03-08","status":"propria","relatorio":16,"temporada":"2022-2023","fonte":"pdf"},{"data":"2023-03-15","status":"propria","relatorio":17,"temporada":"2022-2023","fonte":"pdf"},{"data":"2023-03-20","status":"propria","relatorio":18,"temporada":"2022-2023","fonte":"pdf"},{"data":"2023-03-29","status":"propria","relatorio":19,"temporada":"2022-2023","fonte":"pdf"},{"data":"2023-04-26","status":"propria","relatorio":20,"temporada":"2022-2023","fonte":"pdf"},{"data":"2023-10-25","status":"propria","relatorio":26,"temporada":"2023-2024","fonte":"pdf"},{"data":"2023-11-08","status":"propria","relatorio":27,"temporada":"2023-2024","fonte":"pdf"},{"data":"2023-11-13","status":"propria","relatorio":28,"temporada":"2023-2024","fonte":"pdf"},{"data":"2023-11-22","status":"propria","relatorio":29,"temporada":"2023-2024","fonte":"pdf"},{"data":"2023-11-29","status":"propria","relatorio":30,"temporada":"2023-2024","fonte":"pdf"},{"data":"2023-12-06","status":"propria","relatorio":1,"temporada":"2023-2024","fonte":"pdf"},{"data":"2023-12-13","status":"propria","relatorio":2,"temporada":"2023-2024","fonte":"pdf"},{"data":"2023-12-20","status":"propria","relatorio":3,"temporada":"2023-2024","fonte":"pdf"},{"data":"2023-12-26","status":"propria","relatorio":4,"temporada":"2023-2024","fonte":"pdf"},{"data":"2024-01-02","status":"impropria","relatorio":5,"temporada":"2023-2024","fonte":"pdf"},{"data":"2024-01-08","status":"propria","relatorio":6,"temporada":"2023-2024","fonte":"pdf"},{"data":"2024-01-15","status":"propria","relatorio":10,"temporada":"2023-2024","fonte":"pdf"},{"data":"2024-01-22","status":"propria","relatorio":12,"temporada":"2023-2024","fonte":"pdf"},{"data":"2024-01-29","status":"propria","relatorio":15,"temporada":"2023-2024","fonte":"pdf"},{"data":"2024-02-06","status":"propria","relatorio":18,"temporada":"2023-2024","fonte":"pdf"},{"data":"2024-02-15","status":"propria","relatorio":21,"temporada":"2023-2024","fonte":"pdf"},{"data":"2024-02-20","status":"propria","relatorio":22,"temporada":"2023-2024","fonte":"pdf"},{"data":"2024-02-27","status":"propria","relatorio":25,"temporada":"2023-2024","fonte":"pdf"},{"data":"2024-03-05","status":"propria","relatorio":28,"temporada":"2023-2024","fonte":"pdf"},{"data":"2024-03-12","status":"propria","relatorio":31,"temporada":"2023-2024","fonte":"pdf"},{"data":"2024-03-19","status":"propria","relatorio":34,"temporada":"2023-2024","fonte":"pdf"},{"data":"2024-03-26","status":"propria","relatorio":37,"temporada":"2023-2024","fonte":"pdf"},{"data":"2024-04-24","status":"propria","relatorio":41,"temporada":"2023-2024","fonte":"pdf"},{"data":"2024-05-22","status":"propria","relatorio":45,"temporada":"2023-2024","fonte":"pdf"},{"data":"2024-09-25","status":"propria","relatorio":64,"temporada":"2024-2025","fonte":"pdf"},{"data":"2024-10-08","status":"propria","relatorio":67,"temporada":"2024-2025","fonte":"pdf"},{"data":"2024-10-15","status":"propria","relatorio":70,"temporada":"2024-2025","fonte":"pdf"},{"data":"2024-10-22","status":"propria","relatorio":73,"temporada":"2024-2025","fonte":"pdf"},{"data":"2024-10-30","status":"propria","relatorio":76,"temporada":"2024-2025","fonte":"pdf"},{"data":"2024-11-05","status":"propria","relatorio":1,"temporada":"2024-2025","fonte":"pdf"},{"data":"2024-11-12","status":"propria","relatorio":2,"temporada":"2024-2025","fonte":"pdf"},{"data":"2024-11-21","status":"propria","relatorio":3,"temporada":"2024-2025","fonte":"pdf"},{"data":"2024-11-26","status":"propria","relatorio":4,"temporada":"2024-2025","fonte":"pdf"},{"data":"2024-12-03","status":"propria","relatorio":7,"temporada":"2024-2025","fonte":"pdf"},{"data":"2024-12-10","status":"propria","relatorio":10,"temporada":"2024-2025","fonte":"pdf"},{"data":"2024-12-17","status":"propria","relatorio":13,"temporada":"2024-2025","fonte":"pdf"},{"data":"2024-12-26","status":"propria","relatorio":16,"temporada":"2024-2025","fonte":"pdf"},{"data":"2025-01-02","status":"propria","relatorio":17,"temporada":"2024-2025","fonte":"pdf"},{"data":"2025-01-07","status":"propria","relatorio":18,"temporada":"2024-2025","fonte":"pdf"},{"data":"2025-01-14","status":"propria","relatorio":21,"temporada":"2024-2025","fonte":"pdf"},{"data":"2025-01-28","status":"propria","relatorio":23,"temporada":"2024-2025","fonte":"pdf"},{"data":"2025-02-04","status":"propria","relatorio":26,"temporada":"2024-2025","fonte":"pdf"},{"data":"2025-02-11","status":"propria","relatorio":29,"temporada":"2024-2025","fonte":"pdf"},{"data":"2025-02-18","status":"propria","relatorio":32,"temporada":"2024-2025","fonte":"pdf"},{"data":"2025-02-25","status":"propria","relatorio":34,"temporada":"2024-2025","fonte":"pdf"},{"data":"2025-03-06","status":"propria","relatorio":37,"temporada":"2024-2025","fonte":"pdf"},{"data":"2025-03-11","status":"propria","relatorio":38,"temporada":"2024-2025","fonte":"pdf"},{"data":"2025-03-18","status":"propria","relatorio":41,"temporada":"2024-2025","fonte":"pdf"},{"data":"2025-03-25","status":"propria","relatorio":44,"temporada":"2024-2025","fonte":"pdf"},{"data":"2025-04-28","status":"propria","relatorio":51,"temporada":"2024-2025","fonte":"pdf"},{"data":"2025-05-26","status":"propria","relatorio":55,"temporada":"2024-2025","fonte":"pdf"},{"data":"2025-09-29","status":"propria","relatorio":73,"temporada":"2025-2026","fonte":"pdf"},{"data":"2025-10-06","status":"propria","relatorio":74,"temporada":"2025-2026","fonte":"pdf"},{"data":"2025-10-13","status":"propria","relatorio":75,"temporada":"2025-2026","fonte":"pdf"},{"data":"2025-10-20","status":"propria","relatorio":76,"temporada":"2025-2026","fonte":"pdf"},{"data":"2025-10-27","status":"propria","relatorio":77,"temporada":"2025-2026","fonte":"pdf"},{"data":"2025-11-03","status":"propria","relatorio":78,"temporada":"2025-2026","fonte":"pdf"},{"data":"2025-11-10","status":"propria","relatorio":1,"temporada":"2025-2026","fonte":"pdf"},{"data":"2025-11-17","status":"propria","relatorio":2,"temporada":"2025-2026","fonte":"pdf"},{"data":"2025-11-24","status":"propria","relatorio":3,"temporada":"2025-2026","fonte":"pdf"},{"data":"2025-12-01","status":"propria","relatorio":4,"temporada":"2025-2026","fonte":"pdf"},{"data":"2025-12-08","status":"propria","relatorio":5,"temporada":"2025-2026","fonte":"pdf"},{"data":"2025-12-15","status":"propria","relatorio":6,"temporada":"2025-2026","fonte":"pdf"},{"data":"2025-12-22","status":"propria","relatorio":7,"temporada":"2025-2026","fonte":"pdf"},{"data":"2025-12-29","status":"propria","relatorio":8,"temporada":"2025-2026","fonte":"pdf"},{"data":"2026-01-05","status":"propria","relatorio":9,"temporada":"2025-2026","fonte":"pdf"},{"data":"2026-01-12","status":"propria","relatorio":10,"temporada":"2025-2026","fonte":"pdf"},{"data":"2026-01-19","status":"propria","relatorio":11,"temporada":"2025-2026","fonte":"pdf"},{"data":"2026-01-26","status":"propria","relatorio":12,"temporada":"2025-2026","fonte":"pdf"},{"data":"2026-02-02","status":"propria","relatorio":13,"temporada":"2025-2026","fonte":"pdf"},{"data":"2026-02-09","status":"propria","relatorio":14,"temporada":"2025-2026","fonte":"pdf"},{"data":"2026-02-18","status":"propria","relatorio":15,"temporada":"2025-2026","fonte":"pdf"},{"data":"2026-02-23","status":"propria","relatorio":16,"temporada":"2025-2026","fonte":"pdf"},{"data":"2026-03-02","status":"propria","relatorio":17,"temporada":"2025-2026","fonte":"pdf"},{"data":"2026-03-09","status":"propria","relatorio":18,"temporada":"2025-2026","fonte":"pdf"},{"data":"2026-03-16","status":"propria","relatorio":19,"temporada":"2025-2026","fonte":"pdf"},{"data":"2026-03-24","status":"propria","relatorio":20,"temporada":"2025-2026","fonte":"pdf"},{"data":"2026-03-30","status":"propria","relatorio":21,"temporada":"2025-2026","fonte":"pdf"},{"data":"2026-04-27","status":"propria","relatorio":25,"temporada":"2025-2026","fonte":"pdf"},{"data":"2026-05-25","status":"propria","relatorio":29,"temporada":"2025-2026","fonte":"pdf"}]}